umap/__init__.py
umap/__main__.py
umap/cli.py
umap/core/__init__.py
umap/core/fetch.py
umap/core/plot.py
umap/utils/__init__.py
umap/utils/cache.py
umap/utils/drawing.py
umap/utils/optimization.py
umap/utils/styles.py
umap_osm-3.0.0.dist-info/licenses/LICENSE
umap_osm-3.0.0.dist-info/METADATA
umap_osm-3.0.0.dist-info/WHEEL
umap_osm-3.0.0.dist-info/entry_points.txt
umap_osm-3.0.0.dist-info/top_level.txt
umap_osm-3.0.0.dist-info/RECORD
