Metadata-Version: 2.4
Name: umap-osm
Version: 3.0.0
Summary: Draw beautiful maps from OpenStreetMap with a simple Python API and CLI.
Author: Umutcan Edizaslan
License-Expression: MIT
Project-URL: Homepage, https://github.com/U-C4N/Umap
Requires-Python: >=3.8
License-File: LICENSE
Requires-Dist: geopandas
Requires-Dist: matplotlib
Requires-Dist: osmnx
Requires-Dist: psutil
Requires-Dist: PyYAML
Requires-Dist: numpy
Requires-Dist: shapely
Provides-Extra: dev
Requires-Dist: build; extra == "dev"
Requires-Dist: twine; extra == "dev"
Requires-Dist: pytest; extra == "dev"
Dynamic: license-file
